gnodatapackages/NOTES.txt
gnodatapackages/__init__.py
gnodatapackages/coname_stopwords_gno.csv
gnodatapackages/gen_stopwords_gno.csv
gnodatapackages/gno_checkLang_ft.py
gnodatapackages/gno_coname_stopwords.py
gnodatapackages/gno_gen_stopwords.py
gnodatapackages/gno_name_stopwords.py
gnodatapackages/gno_stopwordcleaning.py
gnodatapackages/gno_stopwords.py
gnodatapackages/gno_uploadfile_clean.py
gnodatapackages/honorifics_remove_gno.csv
gnodatapackages/lid.176.ftz
gnodatapackages/personname_wordsremove_gno.csv
gnodatapackages/stopwords_cn.csv
gnodatapackages-1.3.0.dist-info/LICENSE.txt
gnodatapackages-1.3.0.dist-info/METADATA
gnodatapackages-1.3.0.dist-info/WHEEL
gnodatapackages-1.3.0.dist-info/top_level.txt
gnodatapackages-1.3.1.dist-info/LICENSE.txt
gnodatapackages-1.3.1.dist-info/METADATA
gnodatapackages-1.3.1.dist-info/WHEEL
gnodatapackages-1.3.1.dist-info/top_level.txt
gnodatapackages-1.3.1.dist-info/RECORD
