Metadata-Version: 2.1
Name: gnodatapackages
Version: 1.3.1
Summary: data def packages for gno
Home-page: https://github.com/charmandersgsg/gnodatapackages
Author: charmandersgsg
Author-email: charmandersgsg@gmail.com
License: UNKNOWN
Platform: UNKNOWN
Classifier: Programming Language :: Python :: 3
Classifier: License :: OSI Approved :: MIT License
Classifier: Operating System :: OS Independent
Requires-Python: >=3.6
Requires-Dist: pandas
Requires-Dist: ftfy
Requires-Dist: fasttext
